mavping/__init__.py
mavping/mavping.py
mavping-0.1.0.dist-info/licenses/licenses/LICENSE.MIT
mavping-0.1.0.dist-info/licenses/licenses/NOTE
mavping-0.1.0.dist-info/METADATA
mavping-0.1.0.dist-info/WHEEL
mavping-0.1.0.dist-info/entry_points.txt
mavping-0.1.0.dist-info/top_level.txt
mavping-0.1.0.dist-info/RECORD
