Metadata-Version: 2.4
Name: mavping
Version: 0.1.0
Summary: A Python tool for measuring round-trip time (RTT) using the MAVLink TIMESYNC protocol
Author-email: Thomas Krausemann <Thomas.Krausemann@protonmail.com>
License-Expression: MIT
Project-URL: Homepage, https://github.com/krausemann/mavping
Project-URL: Repository, https://github.com/krausemann/mavping
Project-URL: Issues, https://github.com/krausemann/mavping/issues
Classifier: Development Status :: 5 - Production/Stable
Classifier: Intended Audience :: Science/Research
Classifier: Programming Language :: Python :: 3
Classifier: Operating System :: OS Independent
Classifier: Environment :: Console
Classifier: Topic :: Communications
Classifier: Topic :: Scientific/Engineering
Classifier: Topic :: Software Development :: Testing
Requires-Python: >=3.9
License-File: licenses/LICENSE.MIT
License-File: licenses/NOTE
Requires-Dist: pymavlink>=2.4.37
Requires-Dist: pyserial>=3.5
Dynamic: license-file
